lcs_algorithms/LCS1992.py
lcs_algorithms/MLCS1992.py
lcs_algorithms/MLCS2011.py
lcs_algorithms/RAA2005.py
lcs_algorithms/RRDPLCS.py
lcs_algorithms/TA1997.py
lcs_algorithms/TBA.py
lcs_algorithms/__init__.py
lcs_algorithms-0.1.3.dist-info/licenses/LICENSE
lcs_algorithms-0.1.3.dist-info/METADATA
lcs_algorithms-0.1.3.dist-info/WHEEL
lcs_algorithms-0.1.3.dist-info/top_level.txt
lcs_algorithms-0.1.3.dist-info/RECORD
