Metadata-Version: 2.4
Name: LCS_Algorithms
Version: 0.1.3
Summary: A collection of LCS algorithms in Python
Author: Zeshan Khan
Author-email: Zeshan Khan <zeshankhanalvi@gmail.com>
License: MIT
Project-URL: Homepage, https://github.com/zeshanalvi/lcs_algorithms
Requires-Python: >=3.6
License-File: LICENSE
Dynamic: author
Dynamic: license-file
Dynamic: requires-python
